{
"type": "FeatureCollection",
"name": "Capa sin nombre",
"crs": { "type": "name", "properties": { "name": "urn:ogc:def:crs:OGC:1.3:CRS84" } },
"features": [
{ "type": "Feature", "properties": { "Name": "Portones, San Bernardo" }, "geometry": { "type": "Point", "coordinates": [ -74.4775281, 4.190567, 0.0 ] } }
]
}
